es_template_manager/__init__.py
es_template_manager/es_template_manager.py
es_template_manager-1.3.dist-info/LICENSE
es_template_manager-1.3.dist-info/METADATA
es_template_manager-1.3.dist-info/WHEEL
es_template_manager-1.3.dist-info/entry_points.txt
es_template_manager-1.3.dist-info/top_level.txt
es_template_manager-1.3.dist-info/RECORD
