Metadata-Version: 2.1
Name: es-template-manager
Version: 1.3
Summary: A utility for managing Elasticsearch index templates in source control
Home-page: https://github.com/accorvin/es-template-manager
Author: Alex Corvin
Author-email: accorvin@live.com
License: UNKNOWN
Platform: UNKNOWN
Requires-Dist: requests
Requires-Dist: prometheus-client
